{"agent_group": "ironclaw", "audit": {"access": {"access_count": 0}, "archive": {"http_code": 200, "in_archive_listing": false}, "consolidate": {"consolidated_id": "17a26a23-456b-4b76-83c7-44739a8f3e28", "http_code": 201, "sibling_count": 3}, "expire": {"http_code": 404, "marker_set": false, "still_visible": true}, "promote": {"http_code": 404, "tier_after": null}, "purge": {"http_code": 404, "still_in_archive": false}, "restore": {"active_after_restore": true, "http_code": 404}, "store": {"exists": true, "tier": "mid"}}, "m1_id": "0bc09794-45ff-4309-ba53-ac58c1131cf0", "namespace": "scenario49-lifecycle-7f5061", "pass": false, "reason": "access: access_count not incremented; promote: HTTP 404; promote: tier=None, expected 'long'; expire: HTTP 404; archive: M1 not visible in /api/v1/archive listing; restore: HTTP 404; purge: HTTP 404", "reasons": ["access: access_count not incremented", "promote: HTTP 404", "promote: tier=None, expected 'long'", "expire: HTTP 404", "archive: M1 not visible in /api/v1/archive listing", "restore: HTTP 404", "purge: HTTP 404"], "scenario": "49", "skipped": false, "tls_mode": "off"}
